{
  "type": "SPELL",
  "id": "acid-splash",
  "name": "Acid Splash",
  "url": "/spells/acid-splash",
  "source": "PHB",
  "level": 0,
  "rarity": "COMMON",
  "description": "You hurl a bubble of acid. Choose one creature within range, or choose two creatures within range that are within 5 feet of each other. A target must succeed on a dexterity saving throw or take 1d6 acid damage.\\nThis spell's damage increases by 1d6 when you reach 5th level (2d6), 11th level (3d6), and 17th level (4d6).",
  "range": {
    "type": "RANGED",
    "distance": 60
  },
  "components": {
    "verbal": true,
    "semantic": true,
    "material": false,
    "cost": null,
    "goldValue": 0
  },
  "castingTime": "1 action",
  "duration": "Instantaneous",
  "ritual": false,
  "concentration": false,
  "damage": {
    "type": {
      "id": "acid",
      "name": "Acid",
      "url": "/damage-types/acid"
    },
    "slotLevels": null,
    "characterLevels": {
      "1": "1d6",
      "5": "2d6",
      "11": "3d6",
      "17": "4d6"
    }
  },
  "save": {
    "type": "DEX",
    "onSuccess": null,
    "onFailure": null,
    "extra": null
  },
  "healing": null,
  "areaOfEffect": null,
  "school": {
    "id": "conjuration",
    "name": "Conjuration",
    "url": "/magic-schools/conjuration"
  },
  "classes": [
    {
      "id": "sorcerer",
      "name": "Sorcerer",
      "url": "/classes/sorcerer"
    },
    {
      "id": "wizard",
      "name": "Wizard",
      "url": "/classes/wizard"
    }
  ],
  "scroll": {
    "value": 50,
    "saveDC": 13,
    "attackBonus": 5
  },
  "enchanting": {
    "minLevel": 3,
    "cost": 50,
    "days": 2
  }
}